Metadata-Version: 1.0
Name: qfmath
Version: 0.0.1a0
Summary: qzf math library for python3
Home-page: http://github.com/qzfzz/qmath
Author: bruce
Author-email: qzfzz@163.com
License: MIT
Platform: UNKNOWN
